LICENSE
MANIFEST.in
README.rst
setup.py
bee_django_report/__init__.py
bee_django_report/admin.py
bee_django_report/apps.py
bee_django_report/decorators.py
bee_django_report/dt.py
bee_django_report/exports.py
bee_django_report/forms.py
bee_django_report/models.py
bee_django_report/tests.py
bee_django_report/urls.py
bee_django_report/utils.py
bee_django_report/views.py
bee_django_report.egg-info/PKG-INFO
bee_django_report.egg-info/SOURCES.txt
bee_django_report.egg-info/dependency_links.txt
bee_django_report.egg-info/top_level.txt
bee_django_report/migrations/0001_initial.py
bee_django_report/migrations/0001_initial.pyc
bee_django_report/migrations/0002_auto_20180730_1637.py
bee_django_report/migrations/0002_auto_20180730_1637.pyc
bee_django_report/migrations/0003_report.py
bee_django_report/migrations/0003_report.pyc
bee_django_report/migrations/0004_auto_20190711_1718.py
bee_django_report/migrations/0004_auto_20190711_1718.pyc
bee_django_report/migrations/0005_auto_20190830_1413.py
bee_django_report/migrations/0005_auto_20190830_1413.pyc
bee_django_report/migrations/0006_auto_20190927_1449.py
bee_django_report/migrations/0006_auto_20190927_1449.pyc
bee_django_report/migrations/0007_auto_20191025_1453.py
bee_django_report/migrations/0007_auto_20191025_1453.pyc
bee_django_report/migrations/0008_auto_20191025_1640.py
bee_django_report/migrations/0008_auto_20191025_1640.pyc
bee_django_report/migrations/0009_auto_20191125_1621.py
bee_django_report/migrations/0009_auto_20191125_1621.pyc
bee_django_report/migrations/__init__.py
bee_django_report/migrations/__init__.pyc
bee_django_report/static/bee_django_report/bootstrap/css/bootstrap-theme.min.css
bee_django_report/static/bee_django_report/bootstrap/css/bootstrap.min.css
bee_django_report/static/bee_django_report/bootstrap/fonts/glyphicons-halflings-regular.eot
bee_django_report/static/bee_django_report/bootstrap/fonts/glyphicons-halflings-regular.svg
bee_django_report/static/bee_django_report/bootstrap/fonts/glyphicons-halflings-regular.ttf
bee_django_report/static/bee_django_report/bootstrap/fonts/glyphicons-halflings-regular.woff
